MANIFEST.in
README.md
setup.py
cloud_pretrain.egg-info/PKG-INFO
cloud_pretrain.egg-info/SOURCES.txt
cloud_pretrain.egg-info/dependency_links.txt
cloud_pretrain.egg-info/entry_points.txt
cloud_pretrain.egg-info/requires.txt
cloud_pretrain.egg-info/top_level.txt
cloudpretrain/__init__.py
cloudpretrain/config.py
cloudpretrain/constants.py
cloudpretrain/cli/__init__.py
cloudpretrain/cli/cloudml.py
cloudpretrain/cli/corpus.py
cloudpretrain/cli/datasets.py
cloudpretrain/cli/init.py
cloudpretrain/cli/jobs.py
cloudpretrain/cli/models.py
cloudpretrain/cli/serve.py
cloudpretrain/cli/task.py
cloudpretrain/cli/workspace.py
cloudpretrain/model/__init__.py
cloudpretrain/model/bert_size.py
cloudpretrain/model/job_info.py
cloudpretrain/tasks/__init__.py
cloudpretrain/tasks/bert_basic.py
cloudpretrain/tasks/bert_classifier.py
cloudpretrain/tasks/bert_factory.py
cloudpretrain/tasks/bert_ner.py
cloudpretrain/tasks/bert_preprocess.py
cloudpretrain/tasks/bert_pretraining.py
cloudpretrain/tasks/bert_serve.py
cloudpretrain/tasks/ernie_classifier.py
cloudpretrain/utils/__init__.py
cloudpretrain/utils/cli.py
cloudpretrain/utils/cloudml.py
cloudpretrain/utils/colors.py
cloudpretrain/utils/dataset.py
cloudpretrain/utils/fds.py
cloudpretrain/utils/job.py
cloudpretrain/utils/metrics.py
test/test_fds.py
test/test_priority_class.py
test/test_version.py