Metadata-Version: 1.2
Name: cloud-pretrain
Version: 0.9.post6
Summary: internal tool for Xiaomi AI-LAB with NLP pretrain
Home-page: https://github.com/XiaoMi
Author: Xiaomi AI-LAB NLP-APP
Author-email: zhaoqun3@xiaomi.com
License: MIT
Platform: UNKNOWN
Requires-Python: >=3.6.0
